setup.cfg
setup.py
droidbot/__init__.py
droidbot/app_env.py
droidbot/app_event.py
droidbot/app_state_monitor.py
droidbot/connection.py
droidbot/droidbot.py
droidbot/start.py
droidbot/types.py
droidbot.egg-info/PKG-INFO
droidbot.egg-info/SOURCES.txt
droidbot.egg-info/dependency_links.txt
droidbot.egg-info/entry_points.txt
droidbot.egg-info/requires.txt
droidbot.egg-info/top_level.txt
droidbot/tests/__init__.py
droidbot/tests/app_env_test.py
droidbot/tests/app_event_test.py
droidbot/tests/connection_test.py
droidbot/tests/droidbot_test.py
droidbot/tests/types_test.py
droidbox_script/__init__.py
droidbox_script/bytecode.py
droidbox_script/droidbox.py
droidbox_script/error.py
droidbox_script/monkeyrunner.py
droidbox_script/utils.py