Metadata-Version: 1.1
Name: droidbot
Version: 1.0.0a2
Summary: A smart Android app exerciser.
Home-page: https://github.com/lynnlyc/droidbot
Author: Lynn
Author-email: pkulyc@gmail.com
License: MIT
Download-URL: https://github.com/lynnlyc/droidbot/tarball/1.0.0a2
Keywords: testing,monkey,exerciser
Platform: UNKNOWN
Classifier: Development Status :: 3 - Alpha
Classifier: Intended Audience :: Developers
Classifier: Topic :: Software Development :: Testing
Classifier: License :: OSI Approved :: MIT License
Classifier: Programming Language :: Python :: 2.7
